<?xml version="1.0" encoding="utf-8" ?>
<pluggable type="plugin">
	<name>Pageless</name>
	<version>0.3</version>
	<url>http://code.google.com/p/bcse/wiki/Pageless</url>
	<author url="http://blog.bcse.tw/">Joel Lee</author>
	<license url="http://www.apache.org/licenses/LICENSE-2.0.html">Apache License 2.0</license>
	<description><![CDATA[Give your blog the ability of infinite scrolling, instead of breaking content into ‘pages.’]]></description>
	<copyright>2011</copyright>
	<guid>9b146781-0ee5-406a-aed5-90d661f76ade</guid>
</pluggable>

 
